waymo_open_dataset-1.0.1.dist-info/WHEEL
waymo_open_dataset-1.0.1.dist-info/RECORD
waymo_open_dataset-1.0.1.dist-info/top_level.txt
waymo_open_dataset-1.0.1.dist-info/METADATA
waymo_open_dataset/label_pb2.py
waymo_open_dataset/dataset_pb2.py
waymo_open_dataset/__init__.py
waymo_open_dataset/protos/metrics_pb2.py
waymo_open_dataset/protos/__init__.py
waymo_open_dataset/protos/breakdown_pb2.py
waymo_open_dataset/metrics/__init__.py
waymo_open_dataset/metrics/ops/__init__.py
waymo_open_dataset/metrics/ops/detection_metrics_ops.so
waymo_open_dataset/metrics/ops/py_metrics_ops.py
waymo_open_dataset/metrics/python/__init__.py
waymo_open_dataset/metrics/python/config_util_py.py
waymo_open_dataset/metrics/python/detection_metrics.py
waymo_open_dataset/utils/box_utils.py
waymo_open_dataset/utils/transform_utils.py
waymo_open_dataset/utils/__init__.py
waymo_open_dataset/utils/frame_utils.py
waymo_open_dataset/utils/test_utils.py
waymo_open_dataset/utils/range_image_utils.py
