Metadata-Version: 2.1
Name: waymo-open-dataset
Version: 1.0.1
Summary: Waymo Open Dataset libraries.
Home-page: https://waymo.com/open
Author: Waymo Open Dataset Authors
Author-email: waymo-open-dataset@google.com
License: Apache 2.0
Keywords: autonomous driving dataset machine learning
Platform: UNKNOWN
Classifier: Development Status :: 5 - Production/Stable
Classifier: Intended Audience :: Developers
Classifier: Intended Audience :: Education
Classifier: Intended Audience :: Science/Research
Classifier: License :: OSI Approved :: Apache Software License
Classifier: Programming Language :: Python :: 2.7
Classifier: Programming Language :: Python :: 3.4
Classifier: Programming Language :: Python :: 3.5
Classifier: Programming Language :: Python :: 3.6
Classifier: Topic :: Scientific/Engineering
Classifier: Topic :: Scientific/Engineering :: Artificial Intelligence
Classifier: Topic :: Software Development
Classifier: Topic :: Software Development :: Libraries
Classifier: Topic :: Software Development :: Libraries :: Python Modules
Requires-Python: >=2
Requires-Dist: tensorflow (>=1.14.0)
